{
  "nodes": [
    {
      "id": "8b659d2346456ded",
      "label": "HA Lock Control",
      "position": {
        "x": 397.22010770517534,
        "y": 106.90860370745163
      },
      "data": {
        "inputs": {
          "trigger": {
            "socket": {
              "name": "boolean"
            },
            "label": "Trigger",
            "id": "0ae8c67b6584dbab",
            "control": null,
            "showControl": true
          }
        },
        "outputs": {
          "state": {
            "socket": {
              "name": "any"
            },
            "label": "State",
            "multipleConnections": true,
            "id": "651fd6a145b206ce"
          },
          "is_locked": {
            "socket": {
              "name": "boolean"
            },
            "label": "Is Locked",
            "multipleConnections": true,
            "id": "621100bc4066ff62"
          }
        },
        "controls": {
          "search": {
            "id": "118e527f63f30757",
            "label": "🔍 Search",
            "value": "",
            "placeholder": "Type to filter locks...",
            "type": "text"
          },
          "device_select": {
            "id": "471c4e21cabcb2e6",
            "label": "Lock",
            "values": [
              "— Select Lock —",
              "Aura Reach",
              "Aura Reach"
            ],
            "value": "Aura Reach"
          }
        },
        "label": "HA Lock Control",
        "id": "8b659d2346456ded",
        "width": 280,
        "height": 220,
        "properties": {
          "deviceId": "ha_lock.aura_reach",
          "deviceName": "Aura Reach",
          "searchText": "",
          "currentState": "unavailable",
          "lastTrigger": null
        },
        "devices": [
          {
            "id": "ha_lock.aura_reach",
            "name": "Aura Reach",
            "type": "lock",
            "state": {
              "state": "unavailable",
              "on": false,
              "brightness": 0,
              "hs_color": [
                0,
                0
              ],
              "power": null,
              "energy": null
            },
            "attributes": {
              "friendly_name": "Aura Reach",
              "supported_features": 0
            }
          },
          {
            "id": "ha_lock.aura_reach_2",
            "name": "Aura Reach",
            "type": "lock",
            "state": {
              "state": "unlocked",
              "on": false,
              "brightness": 0,
              "hs_color": [
                0,
                0
              ],
              "power": null,
              "energy": null
            },
            "attributes": {
              "changed_by": "Unknown",
              "friendly_name": "Aura Reach",
              "supported_features": 0
            }
          }
        ],
        "selected": false
      }
    }
  ],
  "connections": [],
  "viewport": {
    "x": -196.57612762451174,
    "y": -94.18662178516388,
    "k": 2.0799220787541923
  },
  "autoSaved": true,
  "timestamp": 1766356469493
}